horapy-0.0.1.dist-info/METADATA
horapy-0.0.1.dist-info/WHEEL
horapy/__init__.py
horapy/horapy.pyd
horapy-0.0.1.dist-info/RECORD
