Metadata-Version: 2.1
Name: horapy
Version: 0.0.1
Classifier: Programming Language :: Python
Classifier: Programming Language :: Rust
Requires-Dist: numpy>=1.6.0
Summary: Hora Search Everywhere
Keywords: intelligence,neighbor,SIMD,search,distance
Home-Page: https://horasearch.com
Author: aljun <gagasalamer@outlook.com>
Author-email: aljun <gagasalamer@outlook.com>
License: Apache-2.0
Project-URL: Source Code, https://github.com/hora-search/hora
